batched/__init__.py
batched/batch_generator.py
batched/batch_processor.py
batched/decorator.py
batched/logger.py
batched/types.py
batched/utils.py
batched/aio/__init__.py
batched/aio/batch_generator.py
batched/aio/batch_processor.py
batched/aio/inference/__init__.py
batched/aio/inference/model_batch_processor.py
batched/inference/__init__.py
batched/inference/helper.py
batched/inference/model_batch_processor.py
batched-0.1.5.dist-info/licenses/LICENSE.md
batched-0.1.5.dist-info/METADATA
batched-0.1.5.dist-info/WHEEL
batched-0.1.5.dist-info/top_level.txt
batched-0.1.5.dist-info/RECORD
