Metadata-Version: 2.4
Name: batched
Version: 0.1.5
Summary: Batched is a flexible and efficient batch processing library implemented in Python. It supports asynchronous batch processing with dynamic batching and prioritization.
Author-email: Mixedbread <support@mixedbread.ai>, Julius Lipp <julius@mixedbread.ai>, Rui Huang <rui@mixedbread.ai>
Requires-Python: >=3.9
License-File: LICENSE.md
Provides-Extra: dev
Requires-Dist: pytest>=8.0.0; extra == "dev"
Requires-Dist: pytest-cov>=4.1.0; extra == "dev"
Requires-Dist: pytest-asyncio>=0.24.0; extra == "dev"
Requires-Dist: ruff>=0.2.0; extra == "dev"
Requires-Dist: pre-commit>=3.6.0; extra == "dev"
Requires-Dist: torch>=2.0.0; extra == "dev"
Requires-Dist: numpy>=1.26.4; extra == "dev"
Dynamic: license-file
